README.md
setup.cfg
setup.py
easyfl/__init__.py
easyfl/config.yaml
easyfl/coordinator.py
easyfl/service.py
easyfl/version.py
easyfl.egg-info/PKG-INFO
easyfl.egg-info/SOURCES.txt
easyfl.egg-info/dependency_links.txt
easyfl.egg-info/not-zip-safe
easyfl.egg-info/requires.txt
easyfl.egg-info/top_level.txt
easyfl/client/__init__.py
easyfl/client/base.py
easyfl/client/service.py
easyfl/communication/__init__.py
easyfl/communication/grpc_wrapper.py
easyfl/compression/__init__.py
easyfl/datasets/__init__.py
easyfl/datasets/data.py
easyfl/datasets/dataset.py
easyfl/datasets/dataset_util.py
easyfl/datasets/simulation.py
easyfl/datasets/cifar10/__init__.py
easyfl/datasets/cifar10/cifar10.py
easyfl/datasets/cifar100/__init__.py
easyfl/datasets/cifar100/cifar100.py
easyfl/datasets/data_process/__init__.py
easyfl/datasets/data_process/cifar10.py
easyfl/datasets/data_process/cifar100.py
easyfl/datasets/data_process/femnist.py
easyfl/datasets/data_process/language_utils.py
easyfl/datasets/data_process/shakespeare.py
easyfl/datasets/femnist/__init__.py
easyfl/datasets/femnist/femnist.py
easyfl/datasets/femnist/preprocess/__init__.py
easyfl/datasets/femnist/preprocess/data_to_json.py
easyfl/datasets/femnist/preprocess/get_file_dirs.py
easyfl/datasets/femnist/preprocess/get_hashes.py
easyfl/datasets/femnist/preprocess/group_by_writer.py
easyfl/datasets/femnist/preprocess/match_hashes.py
easyfl/datasets/shakespeare/__init__.py
easyfl/datasets/shakespeare/shakespeare.py
easyfl/datasets/shakespeare/utils/__init__.py
easyfl/datasets/shakespeare/utils/gen_all_data.py
easyfl/datasets/shakespeare/utils/preprocess_shakespeare.py
easyfl/datasets/shakespeare/utils/shake_utils.py
easyfl/datasets/utils/__init__.py
easyfl/datasets/utils/base_dataset.py
easyfl/datasets/utils/constants.py
easyfl/datasets/utils/download.py
easyfl/datasets/utils/remove_users.py
easyfl/datasets/utils/sample.py
easyfl/datasets/utils/split_data.py
easyfl/datasets/utils/util.py
easyfl/distributed/__init__.py
easyfl/distributed/distributed.py
easyfl/distributed/slurm.py
easyfl/encryption/__init__.py
easyfl/models/__init__.py
easyfl/models/lenet.py
easyfl/models/model.py
easyfl/models/resnet.py
